youtube_dlc/YoutubeDL.py
youtube_dlc/__init__.py
youtube_dlc/__main__.py
youtube_dlc/aes.py
youtube_dlc/cache.py
youtube_dlc/compat.py
youtube_dlc/jsinterp.py
youtube_dlc/options.py
youtube_dlc/socks.py
youtube_dlc/swfinterp.py
youtube_dlc/update.py
youtube_dlc/utils.py
youtube_dlc/version.py
youtube_dlc/downloader/__init__.py
youtube_dlc/downloader/common.py
youtube_dlc/downloader/dash.py
youtube_dlc/downloader/external.py
youtube_dlc/downloader/f4m.py
youtube_dlc/downloader/fragment.py
youtube_dlc/downloader/hls.py
youtube_dlc/downloader/http.py
youtube_dlc/downloader/ism.py
youtube_dlc/downloader/rtmp.py
youtube_dlc/downloader/rtsp.py
youtube_dlc/downloader/youtube_live_chat.py
youtube_dlc/extractor/__init__.py
youtube_dlc/extractor/abc.py
youtube_dlc/extractor/abcnews.py
youtube_dlc/extractor/abcotvs.py
youtube_dlc/extractor/academicearth.py
youtube_dlc/extractor/acast.py
youtube_dlc/extractor/adn.py
youtube_dlc/extractor/adobeconnect.py
youtube_dlc/extractor/adobepass.py
youtube_dlc/extractor/adobetv.py
youtube_dlc/extractor/adultswim.py
youtube_dlc/extractor/aenetworks.py
youtube_dlc/extractor/afreecatv.py
youtube_dlc/extractor/airmozilla.py
youtube_dlc/extractor/aliexpress.py
youtube_dlc/extractor/aljazeera.py
youtube_dlc/extractor/allocine.py
youtube_dlc/extractor/alphaporno.py
youtube_dlc/extractor/alura.py
youtube_dlc/extractor/amcnetworks.py
youtube_dlc/extractor/americastestkitchen.py
youtube_dlc/extractor/amp.py
youtube_dlc/extractor/animeondemand.py
youtube_dlc/extractor/anvato.py
youtube_dlc/extractor/aol.py
youtube_dlc/extractor/apa.py
youtube_dlc/extractor/aparat.py
youtube_dlc/extractor/appleconnect.py
youtube_dlc/extractor/appletrailers.py
youtube_dlc/extractor/archiveorg.py
youtube_dlc/extractor/ard.py
youtube_dlc/extractor/arkena.py
youtube_dlc/extractor/arte.py
youtube_dlc/extractor/asiancrush.py
youtube_dlc/extractor/atresplayer.py
youtube_dlc/extractor/atttechchannel.py
youtube_dlc/extractor/atvat.py
youtube_dlc/extractor/audimedia.py
youtube_dlc-2020.11.11.post3.dist-info/AUTHORS
youtube_dlc-2020.11.11.post3.dist-info/LICENSE
youtube_dlc-2020.11.11.post3.dist-info/METADATA
youtube_dlc-2020.11.11.post3.dist-info/WHEEL
youtube_dlc-2020.11.11.post3.dist-info/entry_points.txt
youtube_dlc-2020.11.11.post3.dist-info/top_level.txt
youtube_dlc-2020.11.11.post3.dist-info/RECORD
